pyeventlib/__init__.py
pyeventlib/arguments.py
pyeventlib/handler.py
pyeventlib-1.1.2.dist-info/LICENSE
pyeventlib-1.1.2.dist-info/METADATA
pyeventlib-1.1.2.dist-info/WHEEL
pyeventlib-1.1.2.dist-info/top_level.txt
pyeventlib-1.1.2.dist-info/RECORD
