Metadata-Version: 2.1
Name: pyeventlib
Version: 1.1.2
Summary: Use event handler simply.
Home-page: https://github.com/DuelitDev/pyeventlib
Author: DuelitDev
Author-email: jyoon07dev@gmail.com
Maintainer: DuelitDev
Maintainer-email: jyoon07dev@gmail.com
Keywords: event,eventhandler,pyevent,pyevents,pyeventlib
Classifier: License :: OSI Approved :: MIT License
Classifier: Programming Language :: Python :: 3.7
Classifier: Programming Language :: Python :: 3.8
Classifier: Programming Language :: Python :: 3.9
Classifier: Programming Language :: Python :: 3.10
Classifier: Programming Language :: Python :: 3.11
Requires-Python: >=3.7
License-File: LICENSE
